graph2img/__init__.py
graph2img/_generate_LaTeX_code.py
graph2img/_graph_functions.py
graph2img-1.3.1.dist-info/LICENSE
graph2img-1.3.1.dist-info/METADATA
graph2img-1.3.1.dist-info/WHEEL
graph2img-1.3.1.dist-info/entry_points.txt
graph2img-1.3.1.dist-info/top_level.txt
graph2img-1.3.1.dist-info/RECORD
