Metadata-Version: 2.1
Name: graph2img
Version: 1.3.1
Summary: graph2img: convert a graph to a png file.
Home-page: https://github.com/ForwardStar/graph_drawer
Author: Haoxuan Xie
Author-email: haoxuanxie@link.cuhk.edu.cn
License: LICENSE
Classifier: Programming Language :: Python :: 3.8
Classifier: License :: OSI Approved :: MIT License
Classifier: Operating System :: OS Independent
Requires-Python: >=3.6
License-File: LICENSE
Requires-Dist: pdf2image>=1.6.0
